Termp/__init__.py
Termp/termp.py
termp-0.2.0.dist-info/LICENSE
termp-0.2.0.dist-info/METADATA
termp-0.2.0.dist-info/WHEEL
termp-0.2.0.dist-info/top_level.txt
termp-0.2.0.dist-info/RECORD
