Metadata-Version: 2.1
Name: termp
Version: 0.2.0
Summary: Draw in terminal
Home-page: https://github.com/dmitrijkotov634/Termp
Author: dmitrijkotov
Author-email: dmitrijkotov634@mail.ru
License: MIT
Keywords: Draw in terminal
Platform: UNKNOWN
Classifier: Programming Language :: Python :: 3
Classifier: Programming Language :: Python :: 3.4
Classifier: Programming Language :: Python :: 3.5
Classifier: Programming Language :: Python :: 3.6
Classifier: Programming Language :: Python :: 3.7
Classifier: License :: OSI Approved :: MIT License
Classifier: Operating System :: OS Independent
Requires-Python: >=3
Requires-Dist: termcolor
Requires-Dist: pillow
